{"propertiesBar":{"properties":[{"name":"About","expanded":true,"children":[]},{"name":"Colors","expanded":true,"children":[]},{"name":"Startup","expanded":true,"children":[]},{"name":"Display","expanded":true,"children":[{"name":"Viewport size","expanded":false,"children":[]}]},{"name":"Advanced","expanded":false,"children":[]},{"name":"Editor","expanded":true,"children":[]}],"scrollPosition":0},"openTabs":{"active":{"name":"Layout 3","type":"layout"},"open":[{"name":"StartPAge","type":"layout"},{"name":"Layout 1","type":"layout"},{"name":"Layout 2","type":"layout"},{"name":"Layout 3","type":"layout"},{"name":"Event sheet 1","type":"eventSheet"},{"name":"Layout 2 Sheet","type":"eventSheet"},{"name":"Layout 3 Sheet","type":"eventSheet"},{"name":"Game Over Layout","type":"layout"}]},"previewEffects":true,"previewBrowser":"default","pauseOnUnfocus":false,"projectBar":{"name":"<root>","children":[{"name":"LoopMAn","expanded":true,"children":[{"name":"Layouts","expanded":true,"children":[{"name":"StartPAge","expanded":true,"children":[]},{"name":"Layout 1","expanded":true,"children":[]},{"name":"Layout 2","expanded":true,"children":[]},{"name":"Layout 3","expanded":true,"children":[]},{"name":"Game Over Layout","expanded":true,"children":[]}]},{"name":"Event sheets","expanded":true,"children":[{"name":"Event sheet 1","expanded":true,"children":[]},{"name":"Event sheet 2","expanded":true,"children":[]},{"name":"Layout 2 Sheet","expanded":true,"children":[]},{"name":"Layout 3 Sheet","expanded":true,"children":[]}]},{"name":"Scripts","expanded":true,"children":[]},{"name":"Object types","expanded":true,"children":[{"name":"ActuallControls","expanded":true,"children":[]},{"name":"Audio","expanded":true,"children":[]},{"name":"Background","expanded":true,"children":[]},{"name":"Bamboo1","expanded":true,"children":[]},{"name":"Bamboo2","expanded":true,"children":[]},{"name":"BG","expanded":true,"children":[]},{"name":"Continue","expanded":true,"children":[]},{"name":"Controls","expanded":true,"children":[]},{"name":"DeadFloor","expanded":true,"children":[]},{"name":"DeadFloor2","expanded":true,"children":[]},{"name":"DoubleJumpScroll","expanded":true,"children":[]},{"name":"EnemyBlock1","expanded":true,"children":[]},{"name":"EnemyBlock2","expanded":true,"children":[]},{"name":"EnemyBlock3","expanded":true,"children":[]},{"name":"EnemyBlock4","expanded":true,"children":[]},{"name":"EnemyBlock5","expanded":true,"children":[]},{"name":"EnemyBlock6","expanded":true,"children":[]},{"name":"EnemyBlock7","expanded":true,"children":[]},{"name":"EnemyBlock8","expanded":true,"children":[]},{"name":"ForeField","expanded":true,"children":[]},{"name":"gameOverDeathScreen","expanded":true,"children":[]},{"name":"Ground","expanded":true,"children":[]},{"name":"HopeBlock2","expanded":true,"children":[]},{"name":"HopeBlock3","expanded":true,"children":[]},{"name":"HopeTurt","expanded":true,"children":[]},{"name":"HopeTurt2","expanded":true,"children":[]},{"name":"HopeTurt3","expanded":true,"children":[]},{"name":"InvincibilityScroll","expanded":true,"children":[]},{"name":"InvisWall","expanded":true,"children":[]},{"name":"InvisWall2","expanded":true,"children":[]},{"name":"ItemBar","expanded":true,"children":[]},{"name":"ItemBoxHolder","expanded":true,"children":[]},{"name":"ItemPhotoPLaceHolder","expanded":true,"children":[]},{"name":"Key","expanded":true,"children":[]},{"name":"Key2","expanded":true,"children":[]},{"name":"Key3","expanded":true,"children":[]},{"name":"Key4","expanded":true,"children":[]},{"name":"Key_Grab","expanded":true,"children":[]},{"name":"Keyboard","expanded":true,"children":[]},{"name":"LifeBar","expanded":true,"children":[]},{"name":"Mouse","expanded":true,"children":[]},{"name":"Music","expanded":true,"children":[]},{"name":"MusicBar","expanded":true,"children":[]},{"name":"NoText","expanded":true,"children":[]},{"name":"OnMusic","expanded":true,"children":[]},{"name":"Plat","expanded":true,"children":[]},{"name":"Plat2","expanded":true,"children":[]},{"name":"Plat3","expanded":true,"children":[]},{"name":"PlatformCOver","expanded":true,"children":[]},{"name":"Platforms","expanded":true,"children":[]},{"name":"Platforms2","expanded":true,"children":[]},{"name":"Player","expanded":true,"children":[]},{"name":"Player2","expanded":true,"children":[]},{"name":"Player3","expanded":true,"children":[]},{"name":"PlayrHP","expanded":true,"children":[]},{"name":"PressI","expanded":true,"children":[]},{"name":"PressIStaionary","expanded":true,"children":[]},{"name":"PressIStaionaryW","expanded":true,"children":[]},{"name":"PressW","expanded":true,"children":[]},{"name":"Sprite","expanded":true,"children":[]},{"name":"Start","expanded":true,"children":[]},{"name":"SuperBG","expanded":true,"children":[]},{"name":"TiledBackground","expanded":true,"children":[]},{"name":"Tilemap","expanded":true,"children":[]},{"name":"Turts","expanded":true,"children":[]},{"name":"Turts10","expanded":true,"children":[]},{"name":"Turts11","expanded":true,"children":[]},{"name":"Turts12","expanded":true,"children":[]},{"name":"Turts13","expanded":true,"children":[]},{"name":"Turts2","expanded":true,"children":[]},{"name":"Turts4","expanded":true,"children":[]},{"name":"Turts5","expanded":true,"children":[]},{"name":"Turts6","expanded":true,"children":[]},{"name":"Turts7","expanded":true,"children":[]},{"name":"Turts8","expanded":true,"children":[]},{"name":"Turts9","expanded":true,"children":[]},{"name":"YesText","expanded":true,"children":[]}]},{"name":"Families","expanded":true,"children":[]},{"name":"Timelines","expanded":false,"children":[{"name":"Eases","expanded":false,"children":[]}]},{"name":"Sounds","expanded":true,"children":[{"name":"Hit.webm","expanded":true,"children":[]},{"name":"JUmp.webm","expanded":true,"children":[]},{"name":"Key.webm","expanded":true,"children":[]},{"name":"Powerup.webm","expanded":true,"children":[]},{"name":"Running.webm","expanded":true,"children":[]},{"name":"Shield.webm","expanded":true,"children":[]},{"name":"Shuriken.webm","expanded":true,"children":[]}]},{"name":"Music","expanded":false,"children":[{"name":"ChunNan - Dragon Road Day - Sonic Unleashed Music Extended [Music OST][Original Soundtrack].mp3","expanded":true,"children":[]},{"name":"Credits - Avatar The Last Airbender Soundtrack.mp3","expanded":true,"children":[]}]},{"name":"Videos","expanded":true,"children":[]},{"name":"Fonts","expanded":true,"children":[]},{"name":"Icons","expanded":false,"children":[{"name":"icon-128.png","expanded":true,"children":[]},{"name":"icon-16.png","expanded":true,"children":[]},{"name":"icon-256.png","expanded":true,"children":[]},{"name":"icon-32.png","expanded":true,"children":[]},{"name":"icon-512.png","expanded":true,"children":[]},{"name":"icon-64.png","expanded":true,"children":[]},{"name":"loading-logo.png","expanded":true,"children":[]}]},{"name":"Files","expanded":true,"children":[]}]}]},"propertiesBarActiveObject":{"name":"Layout 3","type":"layout"}}