{
	"name": "EnemyBlock1",
	"plugin-id": "Sprite",
	"sid": 959429828920548,
	"isGlobal": true,
	"instanceVariables": [],
	"behaviorTypes": [
		{
			"behaviorId": "Bullet",
			"name": "Bullet",
			"sid": 171372293023971
		},
		{
			"behaviorId": "destroy",
			"name": "DestroyOutsideLayout",
			"sid": 178303797493755
		}
	],
	"effectTypes": [],
	"animations": {
		"items": [
			{
				"frames": [
					{
						"width": 117,
						"height": 117,
						"originX": 0.5087441493691495,
						"originY": 0.5755176536426537,
						"originalSource": "C:\\Users\\colom\\OneDrive\\Pictures\\Shuriken.png",
						"exportFormat": "png",
						"exportQuality": 0.8,
						"imageSpriteId": 6440704,
						"collisionPoly": {
							"points": [
								0.3725262006512007,
								0.34848773911273906,
								0.5034022690272691,
								0.010613807488807315,
								0.6356138074888068,
								0.35650055962555954,
								0.9454428673178679,
								0.49271850834350883,
								0.6316073972323967,
								0.642291157916158,
								0.49538944851444855,
								0.9694813288563281,
								0.36451338013838014,
								0.6436266280016275,
								0.04533602971102953,
								0.49538944851444966
							]
						},
						"useCollisionPoly": true,
						"duration": 1
					},
					{
						"width": 117,
						"height": 117,
						"originX": 0.4244823463573463,
						"originY": 0.5087441493691495,
						"originalSource": "C:\\Users\\colom\\OneDrive\\Pictures\\Shuriken.png",
						"exportFormat": "png",
						"exportQuality": 0.8,
						"imageSpriteId": 2329764,
						"collisionPoly": {
							"points": [
								0.651512260887261,
								0.3725262006512007,
								0.9893861925111926,
								0.5034022690272691,
								0.6434994403744405,
								0.6356138074888068,
								0.5072814916564912,
								0.9454428673178679,
								0.357708842083842,
								0.6316073972323967,
								0.030518671143671905,
								0.49538944851444855,
								0.3563733719983725,
								0.3645133801383802,
								0.5046105514855503,
								0.04533602971102957
							]
						},
						"useCollisionPoly": true,
						"duration": 1
					}
				],
				"sid": 920090868921816,
				"name": "Animation 1",
				"isLooping": true,
				"isPingPong": false,
				"repeatCount": 1,
				"repeatTo": 0,
				"speed": 6
			}
		],
		"subfolders": []
	}
}